qimage2ndarray/__init__.py
qimage2ndarray/dynqt.py
qimage2ndarray/qimageview_python.py
qimage2ndarray/qrgb_polyfill.py
qimage2ndarray/qt_driver.py
qimage2ndarray-1.10.0.dist-info/LICENSE.txt
qimage2ndarray-1.10.0.dist-info/METADATA
qimage2ndarray-1.10.0.dist-info/WHEEL
qimage2ndarray-1.10.0.dist-info/top_level.txt
qimage2ndarray-1.10.0.dist-info/RECORD
