Metadata-Version: 2.1
Name: qimage2ndarray
Version: 1.10.0
Summary: Conversion between QImages and numpy.ndarrays.
Home-page: https://github.com/hmeine/qimage2ndarray
Download-URL: https://github.com/hmeine/qimage2ndarray/releases
Author: Hans Meine
Author-email: hans_meine@gmx.net
Keywords: QImage,numpy,ndarray,image,convert,PyQt4,PyQt5,PyQt6,PySide,PySide6
Classifier: Programming Language :: Python
Classifier: Programming Language :: Python :: 3
Classifier: Development Status :: 5 - Production/Stable
Classifier: Intended Audience :: Developers
Classifier: Intended Audience :: Science/Research
Classifier: License :: OSI Approved :: BSD License
Classifier: Operating System :: OS Independent
Classifier: Topic :: Multimedia :: Graphics
Classifier: Topic :: Software Development :: Libraries :: Python Modules
Classifier: Topic :: Software Development :: User Interfaces
Provides-Extra: PyQt4
Provides-Extra: PyQt5
Provides-Extra: PyQt6
Provides-Extra: PySide
Provides-Extra: PySide2
Provides-Extra: PySide6
License-File: LICENSE.txt
